{
  "id": "contact-07",
  "name": "Contact 7",
  "cards": [
    {
      "fr": "une année",
      "nl": "een jaar"
    },
    {
      "fr": "une boule",
      "nl": "een bol"
    },
    {
      "fr": "une boule de Noël",
      "nl": "een kerstbal"
    },
    {
      "fr": "une buche de Noël",
      "nl": "een kerststronk"
    },
    {
      "fr": "un chèque-cadeau",
      "nl": "een geschenkbon"
    },
    {
      "fr": "une fête",
      "nl": "een feest"
    },
    {
      "fr": "une fête de fin d’année",
      "nl": "een eindejaarsfeest"
    },
    {
      "fr": "une guirlande",
      "nl": "een slinger"
    },
    {
      "fr": "le jour de l’An",
      "nl": "nieuwjaarsdag"
    },
    {
      "fr": "Noël",
      "nl": "Kerstmis"
    },
    {
      "fr": "un repas",
      "nl": "een maaltijd"
    },
    {
      "fr": "le réveillon (de Noël)",
      "nl": "kerstavond"
    },
    {
      "fr": "le réveillon (du jour de l’An)",
      "nl": "oudejaarsavond"
    },
    {
      "fr": "la Saint-Nicolas",
      "nl": "het sinterklaasfeest"
    },
    {
      "fr": "un sapin de Noël",
      "nl": "een kerstboom"
    },
    {
      "fr": "une surprise",
      "nl": "een verrassing"
    },
    {
      "fr": "décorer",
      "nl": "versieren"
    },
    {
      "fr": "mettre",
      "nl": "zetten, plaatsen"
    },
    {
      "fr": "je mets",
      "nl": "ik zet, ik plaats"
    },
    {
      "fr": "il / elle met",
      "nl": "hij / zij zet, plaatst"
    },
    {
      "fr": "ils / elles mettent",
      "nl": "zij zetten, plaatsen"
    },
    {
      "fr": "ouvrir",
      "nl": "openen"
    },
    {
      "fr": "agréable",
      "nl": "aangenaam, gezellig"
    },
    {
      "fr": "avant",
      "nl": "voor (tijd)"
    },
    {
      "fr": "en cela",
      "nl": "daarin"
    },
    {
      "fr": "quelques",
      "nl": "enkele, enige"
    },
    {
      "fr": "une année",
      "nl": "une boule"
    },
    {
      "fr": "une buche de Noël",
      "nl": "un chèque-cadeau"
    },
    {
      "fr": "une fête de fin d’année",
      "nl": "une guirlande"
    },
    {
      "fr": "Noël",
      "nl": "un repas"
    },
    {
      "fr": "le réveillon (du jour de l’An)",
      "nl": "la Saint-Nicolas"
    },
    {
      "fr": "une surprise",
      "nl": "décorer"
    },
    {
      "fr": "je mets",
      "nl": "il / elle met"
    },
    {
      "fr": "ouvrir",
      "nl": "agréable"
    },
    {
      "fr": "en cela",
      "nl": "quelques"
    },
    {
      "fr": "een kerstbal",
      "nl": "een bol"
    },
    {
      "fr": "een feest",
      "nl": "een geschenkbon"
    },
    {
      "fr": "nieuwjaarsdag",
      "nl": "een slinger"
    },
    {
      "fr": "kerstavond",
      "nl": "een maaltijd"
    },
    {
      "fr": "een kerstboom",
      "nl": "het sinterklaasfeest"
    },
    {
      "fr": "zetten, plaatsen",
      "nl": "versieren"
    },
    {
      "fr": "zij zetten, plaatsen",
      "nl": "hij/ zij zet, plaatst"
    },
    {
      "fr": "voor (tijd)",
      "nl": "aangenaam, gezellig"
    },
    {
      "fr": "enkele, enige",
      "nl": "daarin"
    }
  ]
}